{
  "responses": [
    {
      "labelAnnotations": [
        {
          "description": "Publication",
          "mid": "/m/01h1dd",
          "score": 0.8566029,
          "topicality": 0.002628879
        },
        {
          "description": "Book",
          "mid": "/m/0bt_c3",
          "score": 0.8139752,
          "topicality": 0.48826945
        },
        {
          "description": "Nail",
          "mid": "/m/023j4r",
          "score": 0.6907924,
          "topicality": 0.0005720917
        },
        {
          "description": "Learning",
          "mid": "/m/0191f8",
          "score": 0.6532076,
          "topicality": 0.030122407
        },
        {
          "description": "Reading",
          "mid": "/m/04yclrg",
          "score": 0.6186852,
          "topicality": 0.6513991
        }
      ]
    }
  ]
}
