{
  "responses": [
    {
      "labelAnnotations": [
        {
          "description": "Smile",
          "mid": "/m/019nj4",
          "score": 0.99271655,
          "topicality": 0.41718864
        },
        {
          "description": "Happiness",
          "mid": "/m/016pp7",
          "score": 0.9850962,
          "topicality": 0.0127876345
        },
        {
          "description": "Lips",
          "mid": "/m/06pj2k",
          "score": 0.9847835,
          "topicality": 0.012403102
        },
        {
          "description": "Jaw",
          "mid": "/m/01k9lj",
          "score": 0.9724436,
          "topicality": 0.07031975
        },
        {
          "description": "Facial expression",
          "mid": "/m/01k74n",
          "score": 0.94494975,
          "topicality": 0.007968574
        },
        {
          "description": "Tooth",
          "mid": "/m/0cnxs6x",
          "score": 0.9361486,
          "topicality": 0.7367971
        },
        {
          "description": "Facial hair",
          "mid": "/m/0ds5b",
          "score": 0.84920895,
          "topicality": 0.0025417698
        },
        {
          "description": "Laughter",
          "mid": "/m/01j3sz",
          "score": 0.8129267,
          "topicality": 0.059311803
        },
        {
          "description": "Pleased",
          "mid": "/j/4kr7kk",
          "score": 0.79770344,
          "topicality": 0.0003126879
        },
        {
          "description": "Wrinkle",
          "mid": "/m/02_x63",
          "score": 0.7745596,
          "topicality": 0.0016960298
        }
      ]
    }
  ]
}
